aidocs_cli/__init__.py
aidocs_cli/chunker.py
aidocs_cli/cli.py
aidocs_cli/coverage.py
aidocs_cli/embeddings.py
aidocs_cli/installer.py
aidocs_cli/mcp_server.py
aidocs_cli/pdf_exporter.py
aidocs_cli/server.py
aidocs_cli/watcher.py
aidocs_cli/templates/commands/docs/analyze.md
aidocs_cli/templates/commands/docs/batch.md
aidocs_cli/templates/commands/docs/discover.md
aidocs_cli/templates/commands/docs/execute.md
aidocs_cli/templates/commands/docs/explore.md
aidocs_cli/templates/commands/docs/export-pdf.md
aidocs_cli/templates/commands/docs/flow.md
aidocs_cli/templates/commands/docs/generate.md
aidocs_cli/templates/commands/docs/init.md
aidocs_cli/templates/commands/docs/plan.md
aidocs_cli/templates/commands/docs/rag-init.md
aidocs_cli/templates/commands/docs/rag-vectors.md
aidocs_cli/templates/commands/docs/rag.md
aidocs_cli/templates/commands/docs/update.md
aidocs_cli/templates/workflows/analyze/workflow.md
aidocs_cli/templates/workflows/batch/workflow.md
aidocs_cli/templates/workflows/discover/workflow.md
aidocs_cli/templates/workflows/execute/workflow.md
aidocs_cli/templates/workflows/explore/workflow.md
aidocs_cli/templates/workflows/export-pdf/workflow.md
aidocs_cli/templates/workflows/flow/highlight-utils.js
aidocs_cli/templates/workflows/flow/workflow.md
aidocs_cli/templates/workflows/generate/workflow.md
aidocs_cli/templates/workflows/init/workflow.md
aidocs_cli/templates/workflows/plan/workflow.md
aidocs_cli/templates/workflows/rag/workflow.md
aidocs_cli/templates/workflows/rag-init/workflow.md
aidocs_cli/templates/workflows/rag-vectors/workflow.md
aidocs_cli/templates/workflows/templates/page-doc.template.md
aidocs_cli/templates/workflows/update/workflow.md
aidocs-0.18.0.dist-info/METADATA
aidocs-0.18.0.dist-info/WHEEL
aidocs-0.18.0.dist-info/entry_points.txt
aidocs-0.18.0.dist-info/licenses/LICENSE
aidocs-0.18.0.dist-info/RECORD
