Metadata-Version: 2.4
Name: aidocs
Version: 0.18.0
Summary: AI-powered documentation generator for web applications. Install docs commands into your Claude Code project.
Project-URL: Homepage, https://github.com/binarcode/aidocs-cli
Project-URL: Repository, https://github.com/binarcode/aidocs-cli
Project-URL: Issues, https://github.com/binarcode/aidocs-cli/issues
License: MIT
License-File: LICENSE
Keywords: ai,automation,claude,documentation,playwright
Classifier: Development Status :: 4 - Beta
Classifier: Environment :: Console
Classifier: Intended Audience :: Developers
Classifier: License :: OSI Approved :: MIT License
Classifier: Operating System :: OS Independent
Classifier: Programming Language :: Python :: 3
Classifier: Programming Language :: Python :: 3.11
Classifier: Programming Language :: Python :: 3.12
Classifier: Topic :: Documentation
Classifier: Topic :: Software Development :: Documentation
Requires-Python: >=3.11
Requires-Dist: httpx>=0.27.0
Requires-Dist: mcp>=1.0.0
Requires-Dist: mkdocs-material>=9.5.0
Requires-Dist: mkdocs>=1.6.0
Requires-Dist: python-dotenv>=1.0.0
Requires-Dist: pyyaml>=6.0
Requires-Dist: rich>=13.0.0
Requires-Dist: typer>=0.9.0
Requires-Dist: watchdog>=4.0.0
